README.md
setup.py
src/sentry_wechat/__init__.py
src/sentry_wechat/forms.py
src/sentry_wechat/plugin.py
src/sentry_wechat.egg-info/PKG-INFO
src/sentry_wechat.egg-info/SOURCES.txt
src/sentry_wechat.egg-info/dependency_links.txt
src/sentry_wechat.egg-info/entry_points.txt
src/sentry_wechat.egg-info/not-zip-safe
src/sentry_wechat.egg-info/requires.txt
src/sentry_wechat.egg-info/top_level.txt