Metadata-Version: 2.1
Name: sentry-wechat
Version: 0.0.3
Summary: A sentry extension which share information to Wechat Work
Home-page: https://github.com/corcd/sentry-wechat
Author: whzcorcd
Author-email: whzcorcd@gmail.com
License: MIT
Keywords: sentry wechat
Platform: UNKNOWN
Classifier: Programming Language :: Python :: 2.7
Classifier: License :: OSI Approved :: MIT License
